<?xml version="1.0" encoding="utf-8" ?>
<dwsync>
<file name="1.fw.png" server="210.70.168.17/Appserv/www/" local="130155415820259274" remote="130155870600000000" Dst="0" />
<file name="10.fw.png" server="210.70.168.17/Appserv/www/" local="130155421068919480" remote="130155870600000000" Dst="0" />
<file name="11.fw.png" server="210.70.168.17/Appserv/www/" local="130155421327734284" remote="130155871200000000" Dst="0" />
<file name="2.fw.png" server="210.70.168.17/Appserv/www/" local="130155416239463251" remote="130155871200000000" Dst="0" />
<file name="3.fw.png" server="210.70.168.17/Appserv/www/" local="130155416849238128" remote="130155871200000000" Dst="0" />
<file name="4.fw.png" server="210.70.168.17/Appserv/www/" local="130155417225339640" remote="130155871200000000" Dst="0" />
<file name="5.fw.png" server="210.70.168.17/Appserv/www/" local="130155417576389719" remote="130155871200000000" Dst="0" />
<file name="6.fw.png" server="210.70.168.17/Appserv/www/" local="130155418032165788" remote="130155871800000000" Dst="0" />
<file name="7.fw.png" server="210.70.168.17/Appserv/www/" local="130155418306691490" remote="130155871800000000" Dst="0" />
<file name="8.fw.png" server="210.70.168.17/Appserv/www/" local="130155418460130266" remote="130155871800000000" Dst="0" />
<file name="9.fw.png" server="210.70.168.17/Appserv/www/" local="130155420904080052" remote="130155871800000000" Dst="0" />
</dwsync>